<?xml version="1.0" encoding="utf-8" ?>
<resources>
    <color name="primaryColor">#51629a</color>
    <color name="primaryDarkColor">#51629a</color>
    <color name="primaryLightColor">#6f7bb8</color>

    <color name="accentColor">#4c555a</color>
    <color name="accentDarkColor">#242c31</color>
    <color name="accentLightColor">#788187</color>

    <color name="primaryTextColor">#56595e</color>
    <color name="secondaryTextColor">#ffffff</color>

    <color name="enabledButtonColor">#edcf2b</color>
    <color name="disabledButtonColor">#e5e8ef</color>
    <color name="pressedButtonColor">@color/primaryLightColor</color>
</resources>
